{"version":1,"resource":"file:///home/user/webpages_tech/demo_tech_educators/style.css","entries":[{"id":"EmKd.css","timestamp":1695031354205},{"id":"X800.css","timestamp":1695031379565},{"id":"YeXn.css","timestamp":1695031392121},{"id":"ZutY.css","timestamp":1695031439676},{"id":"nmL3.css","timestamp":1695031542848},{"id":"CC39.css","timestamp":1695031633088},{"id":"ZXni.css","timestamp":1695031664136},{"id":"leOt.css","timestamp":1695031709520},{"id":"7DRt.css","timestamp":1695031727656},{"id":"aBwY.css","timestamp":1695031763584},{"id":"Stuu.css","timestamp":1695031794016},{"id":"EiW1.css","timestamp":1695031804688},{"id":"5AtP.css","timestamp":1695031909093},{"id":"bCwO.css","timestamp":1695031933989},{"id":"DLxC.css","timestamp":1695031962641},{"id":"KuYs.css","timestamp":1695032064069},{"id":"WDWo.css","timestamp":1695032084177},{"id":"eqEn.css","timestamp":1695032107729},{"id":"iIMi.css","timestamp":1695032127345},{"id":"kRyn.css","timestamp":1695032194505},{"id":"hkn1.css","timestamp":1695032231897},{"id":"MIi8.css","timestamp":1695032281614},{"id":"f9GB.css","timestamp":1695032366350},{"id":"LOfN.css","timestamp":1695032385618},{"id":"J2KO.css","timestamp":1695032402686},{"id":"bEDS.css","timestamp":1695032439074},{"id":"k3pj.css","timestamp":1695033471794},{"id":"pyTv.css","timestamp":1695033517587},{"id":"mINz.css","timestamp":1695033540335},{"id":"gL5C.css","timestamp":1695033573707},{"id":"xVz4.css","timestamp":1695033585815},{"id":"2in1.css","timestamp":1695034273042},{"id":"FNjZ.css","timestamp":1695034369950},{"id":"tbDi.css","timestamp":1695034429779},{"id":"9tI4.css","timestamp":1695034468247},{"id":"YjIs.css","timestamp":1695034503719},{"id":"BF6X.css","timestamp":1695034521495},{"id":"8A87.css","timestamp":1695034549759},{"id":"j3Rg.css","timestamp":1695034597883},{"id":"bjsd.css","timestamp":1695034622028},{"id":"Hl7H.css","timestamp":1695034652100},{"id":"MB6z.css","timestamp":1695034720900},{"id":"iZy8.css","timestamp":1695034743408},{"id":"WfFX.css","timestamp":1695034777296},{"id":"nXy2.css","timestamp":1695036270457},{"id":"RqyQ.css","timestamp":1695036564784},{"id":"JEe9.css","timestamp":1695036579828},{"id":"QFXN.css","timestamp":1695037526371},{"id":"Jts0.css","timestamp":1695037878380},{"id":"kl14.css","timestamp":1695037979332}]}